LICENSE
README.md
setup.cfg
setup.py
Cerner_HealtheIntent.egg-info/PKG-INFO
Cerner_HealtheIntent.egg-info/SOURCES.txt
Cerner_HealtheIntent.egg-info/dependency_links.txt
Cerner_HealtheIntent.egg-info/top_level.txt
healtheintentAPI/__init__.py
healtheintentAPI/healtheintentAPI.py