Metadata-Version: 2.1
Name: Cerner-HealtheIntent
Version: 0.0.1
Summary: A wrapper following HealtheIntent open development services which allow access to population health concepts using RESTful APIs.
Home-page: https://github.com/patrickgagnon/Cerner-HealtheIntent
Author: Patrick Gagnon
License: UNKNOWN
Platform: UNKNOWN
License-File: LICENSE
